{
	"name": "PL_INT_DIM_COMPANY_HOUSE",
	"properties": {
		"activities": [
			{
				"name": "SP_INT_DIM_COMPANY_HOUSE",
				"type": "SqlServerStoredProcedure",
				"state": "Inactive",
				"onInactiveMarkAs": "Succeeded",
				"dependsOn": [
					{
						"activity": "SC_SET_DELETIONS_INACTIVE",
						"dependencyConditions": [
							"Succeeded"
						]
					}
				],
				"policy": {
					"timeout": "0.12:00:00",
					"retry": 0,
					"retryIntervalInSeconds": 30,
					"secureOutput": false,
					"secureInput": false
				},
				"userProperties": [],
				"typeProperties": {
					"storedProcedureName": "[KNE_INTSP].[DIM_COMPANY_HOUSE]"
				},
				"linkedServiceName": {
					"referenceName": "LS_Azure_Destination",
					"type": "LinkedServiceReference"
				}
			},
			{
				"name": "SC_SET_DELETIONS_INACTIVE",
				"type": "Script",
				"dependsOn": [],
				"policy": {
					"timeout": "0.12:00:00",
					"retry": 0,
					"retryIntervalInSeconds": 30,
					"secureOutput": false,
					"secureInput": false
				},
				"userProperties": [],
				"linkedServiceName": {
					"referenceName": "LS_Azure_Destination",
					"type": "LinkedServiceReference"
				},
				"typeProperties": {
					"scripts": [
						{
							"type": "Query",
							"text": "UPDATE KNE_INT.DIM_COMPANY_HOUSE\nSET COMPANY_HOUSE_ACT_IND='N'\nWHERE COMPANY_HOUSE_BK\nIN\n(SELECT COMPANY_NUMBER\nFROM KNE_STG.COMPANY_HOUSE_DELETIONS)"
						}
					],
					"scriptBlockExecutionTimeout": "02:00:00"
				}
			}
		],
		"folder": {
			"name": "2_0_INTEGRATION"
		},
		"annotations": []
	}
}